ullyses_utils/__init__.py
ullyses_utils/match_aliases.py
ullyses_utils/parse_csv.py
ullyses_utils/readwrite_yaml.py
ullyses_utils/select_pids.py
ullyses_utils/write_calibration_db.py
ullyses_utils/data/calibration_metadata/ullyses_calibration_db.csv
ullyses_utils/data/calibration_metadata/ullyses_custom_coadd.csv
ullyses_utils/data/calibration_metadata/ullyses_quality_comments.csv
ullyses_utils/data/calibration_metadata/ullyses_rejected_data.csv
ullyses_utils/data/calibration_metadata/ullyses_stisblazefix.csv
ullyses_utils/data/cos_shifts/lmc079-1_shifts.txt
ullyses_utils/data/cos_shifts/sz-10_shifts.txt
ullyses_utils/data/cos_shifts/v-gm-aur_shifts.txt
ullyses_utils/data/cos_shifts/v-tw-hya_shifts.txt
ullyses_utils/data/fuse/bad_fuse_targs.yaml
ullyses_utils/data/fuse/fuse_dq_flagging.yaml
ullyses_utils/data/fuse/good_fuse_targs.yaml
ullyses_utils/data/lcogt_catalogs/2MASS-J11432669M7804454_apass.txt
ullyses_utils/data/lcogt_catalogs/CHX-18N_apass.txt
ullyses_utils/data/lcogt_catalogs/CVSO-104_apass.txt
ullyses_utils/data/lcogt_catalogs/CVSO-107_apass.txt
ullyses_utils/data/lcogt_catalogs/CVSO-109_apass.txt
ullyses_utils/data/lcogt_catalogs/CVSO-146_apass.txt
ullyses_utils/data/lcogt_catalogs/CVSO-165_apass.txt
ullyses_utils/data/lcogt_catalogs/CVSO-176_apass.txt
ullyses_utils/data/lcogt_catalogs/CVSO-17_apass.txt
ullyses_utils/data/lcogt_catalogs/CVSO-36_apass.txt
ullyses_utils/data/lcogt_catalogs/CVSO-58_apass.txt
ullyses_utils/data/lcogt_catalogs/CVSO-90_apass.txt
ullyses_utils/data/lcogt_catalogs/ECHA-J0844M7833_apass.txt
ullyses_utils/data/lcogt_catalogs/HD-104237E_apass.txt
ullyses_utils/data/lcogt_catalogs/HN-5_apass.txt
ullyses_utils/data/lcogt_catalogs/RECX-5_apass.txt
ullyses_utils/data/lcogt_catalogs/RECX-6_apass.txt
ullyses_utils/data/lcogt_catalogs/RECX-9_apass.txt
ullyses_utils/data/lcogt_catalogs/RX-J0438P1546_apass.txt
ullyses_utils/data/lcogt_catalogs/RX-J1556M3655_apass.txt
ullyses_utils/data/lcogt_catalogs/RX-J1842M3532_apass.txt
ullyses_utils-3.1.0.dist-info/METADATA
ullyses_utils-3.1.0.dist-info/WHEEL
ullyses_utils-3.1.0.dist-info/top_level.txt
ullyses_utils-3.1.0.dist-info/RECORD
