Metadata-Version: 2.1
Name: ullyses-utils
Version: 3.1.0
Summary: ULLYSES utility files and scripts
Author-email: ULLYSES STScI Team <ullyses_dp@stsci.edu>
Keywords: astronomy,jwst,simulations
Classifier: Programming Language :: Python
Classifier: Programming Language :: Python :: 3
Classifier: Development Status :: 1 - Planning
Classifier: Intended Audience :: Science/Research
Classifier: Topic :: Scientific/Engineering :: Astronomy
Classifier: Topic :: Scientific/Engineering :: Physics
Classifier: Topic :: Software Development :: Libraries :: Python Modules
Requires-Python: >=3.8
Requires-Dist: numpy
Requires-Dist: astropy
